[
  { "title": "나 혼자만 레벨업", "author": "추공", "genre": "액션/판타지" },
  { "title": "외모지상주의", "author": "박태준", "genre": "액션/학원" },
  { "title": "유미의 세포들", "author": "이동건", "genre": "로맨스" },
  { "title": "신의 탑", "author": "SIU", "genre": "판타지/액션" },
  { "title": "노블레스", "author": "손제호/이광수", "genre": "액션/판타지" },
  { "title": "갓 오브 하이스쿨", "author": "박용제", "genre": "액션/무협" },
  { "title": "마음의 소리", "author": "조석", "genre": "일상/개그" },
  { "title": "여신강림", "author": "야옹이", "genre": "로맨스/학원" },
  { "title": "연애혁명", "author": "민송아", "genre": "로맨스/학원" },
  { "title": "기기괴괴 성형수", "author": "오성대", "genre": "스릴러/공포" },
  { "title": "사신소년", "author": "강지", "genre": "판타지/액션" },
  { "title": "복학왕", "author": "기안84", "genre": "일상/개그" },
  { "title": "입학용병", "author": "YC", "genre": "액션/학원" },
  { "title": "이두나!", "author": "민송아", "genre": "로맨스" },
  { "title": "내 ID는 강남미인!", "author": "Maenggi", "genre": "로맨스/학원" },
  { "title": "냐한남자", "author": "도전만화", "genre": "일상/개그" },
  { "title": "유약무쌍", "author": "하리", "genre": "로맨스/사극" },
  { "title": "퀘스트지상주의", "author": "Insal", "genre": "판타지/액션" },
  { "title": "전지적 독자 시점", "author": "싱숑/UMI", "genre": "판타지/액션" },
  { "title": "템빨", "author": "장태석", "genre": "판타지/액션" },
  { "title": "화산귀환", "author": "비가/Lico", "genre": "무협/액션" },
  { "title": "천마신교 학교에 가다", "author": "윤민/Seo kaya", "genre": "무협/학원" },
  { "title": "무림서생", "author": "제이식", "genre": "무협/로맨스" },
  { "title": "마검왕", "author": "박성규", "genre": "무협/판타지" },
  { "title": "절대검감", "author": "Buryong/H형제", "genre": "무협/액션" },
  { "title": "먹는 존재", "author": "LICO", "genre": "판타지/액션" },
  { "title": "독보적 존재", "author": "IronHwang", "genre": "판타지/액션" },
  { "title": "프리드로우", "author": "전선욱", "genre": "스포츠" },
  { "title": "하이큐!!와 비슷한", "author": "-", "genre": "스포츠" },
  { "title": "열혈강호", "author": "전형진/양재현", "genre": "무협/액션" },
  { "title": "재혼황후", "author": "알파타르트/Sumpul", "genre": "로맨스/판타지" },
  { "title": "황후의 품격", "author": "Pico", "genre": "로맨스/판타지" },
  { "title": "악녀는 모래시계를 되돌린다", "author": "Sansobee/Sumpul", "genre": "로맨스/판타지" },
  { "title": "내가 죽기로 결심한 것은", "author": "Lun Lun", "genre": "로맨스/드라마" },
  { "title": "어느 날 공주가 되어버렸다", "author": "Spoon/Ant Studio", "genre": "로맨스/판타지" },
  { "title": "버림받은 왕녀의 은밀한 침실", "author": "Eunhyuk Ji/GYOM", "genre": "로맨스/판타지" },
  { "title": "나 혼자 신화급", "author": "Ryu Seol", "genre": "판타지/액션" },
  { "title": "듀얼 플레이어", "author": "LICO", "genre": "판타지/게임" },
  { "title": "귀환자의 마법은 특별해야 합니다", "author": "Usonan/Wookjakga", "genre": "판타지/액션" },
  { "title": "나는 용병단장이었다", "author": "박규태", "genre": "판타지/액션" },
  { "title": "고수", "author": "강병건/류기운", "genre": "무협/액션" },
  { "title": "검술명가 막내아들", "author": "크레타/이유진", "genre": "판타지/액션" },
  { "title": "SSS급 자살헌터", "author": "Shin Noah/Illustrated by Neulbo", "genre": "판타지/액션" },
  { "title": "히어로 킬러", "author": "기안84", "genre": "액션/개그" },
  { "title": "스위트홈", "author": "김칸비/황영찬", "genre": "스릴러/공포" },
  { "title": "이태원 클라쓰", "author": "광진", "genre": "드라마/청춘" },
  { "title": "치즈인더트랩", "author": "순끼", "genre": "로맨스/학원" },
  { "title": "미생", "author": "윤태호", "genre": "드라마/직장" },
  { "title": "송곳", "author": "최규석", "genre": "드라마/사회" },
  { "title": "킬링 스토킹", "author": "쿨량", "genre": "스릴러/BL" },
  { "title": "나쁜 기억 지우개", "author": "Massstar", "genre": "로맨스" },
  { "title": "아일랜드", "author": "현민", "genre": "판타지/액션" },
  { "title": "닥터 최태수", "author": "Lee Jung-min", "genre": "드라마/의학" },
  { "title": "브레이커", "author": "전극진/박진환", "genre": "무협/액션" },
  { "title": "테러맨", "author": "한현동", "genre": "액션/스릴러" },
  { "title": "조선왕조실톡", "author": "무적핑크", "genre": "역사/개그" },
  { "title": "위대한 개탁이", "author": "박규태", "genre": "개그/일상" },
  { "title": "덴마", "author": "양영순", "genre": "SF/액션" },
  { "title": "앙마", "author": "강풀", "genre": "드라마/공포" },
  { "title": "26년", "author": "강풀", "genre": "드라마/역사" },
  { "title": "순정만화", "author": "강풀", "genre": "로맨스/드라마" },
  { "title": "아파트", "author": "강풀", "genre": "공포/스릴러" },
  { "title": "바보", "author": "강풀", "genre": "드라마/로맨스" },
  { "title": "이웃사람", "author": "강풀", "genre": "스릴러/드라마" },
  { "title": "무빙", "author": "강풀", "genre": "액션/드라마" },
  { "title": "패션왕", "author": "기안84", "genre": "개그/학원" },
  { "title": "대학일기", "author": "자까", "genre": "일상/개그" },
  { "title": "유부녀의 일기", "author": "민송아", "genre": "일상/드라마" },
  { "title": "시맨틱 에러", "author": "Jeo Sooji/Angy Kim", "genre": "로맨스/BL" },
  { "title": "내 남편과 결혼해줘", "author": "이하은", "genre": "로맨스/드라마" },
  { "title": "후아유", "author": "Narak", "genre": "로맨스/판타지" },
  { "title": "나 혼자 만렙 뉴비", "author": "Shin Noah", "genre": "판타지/액션" },
  { "title": "회귀자의 마법서", "author": "한유림", "genre": "판타지/액션" },
  { "title": "무한의 마법사", "author": "Lee Dong-uk", "genre": "판타지/액션" },
  { "title": "성스러운 탑", "author": "SIU", "genre": "판타지/액션" },
  { "title": "불사인생", "author": "LICO", "genre": "판타지/액션" },
  { "title": "하렘의 남자들", "author": "야옹이", "genre": "로맨스" },
  { "title": "내 방에 이상한 게 들어왔다", "author": "Studio Blackhole", "genre": "공포/스릴러" },
  { "title": "오! 주인님", "author": "야옹이", "genre": "로맨스" },
  { "title": "마왕이 되겠다", "author": "Sansobee", "genre": "판타지/로맨스" },
  { "title": "독립일기", "author": "자까", "genre": "일상/개그" },
  { "title": "놓지마 정신줄", "author": "신태훈/나승훈", "genre": "개그/일상" },
  { "title": "유리벽", "author": "윤태호", "genre": "드라마/스릴러" },
  { "title": "은밀하게 위대하게", "author": "Hun", "genre": "액션/드라마" },
  { "title": "언어의 온도", "author": "이기주", "genre": "에세이" },
  { "title": "봉제인형 살인사건", "author": "LICO", "genre": "스릴러/공포" },
  { "title": "더 게이머", "author": "성기운/정규진", "genre": "판타지/게임" },
  { "title": "갓 오브 블랙필드", "author": "황문호/NICKE", "genre": "판타지/액션" },
  { "title": "탑툰에서 살아남기", "author": "-", "genre": "판타지/이세계" },
  { "title": "혼자 사는 오늘", "author": "자까", "genre": "일상/개그" },
  { "title": "사생팬은 그만하고 싶어", "author": "Gaji", "genre": "로맨스" },
  { "title": "네가 있어야 할 곳", "author": "조석", "genre": "드라마" },
  { "title": "나쁜녀석들", "author": "양경일", "genre": "액션/스릴러" },
  { "title": "로어 올림푸스", "author": "Rachel Smythe", "genre": "신화/로맨스" },
  { "title": "빅스마일", "author": "전형진", "genre": "드라마" },
  { "title": "가우스전자", "author": "곽백수", "genre": "직장/개그" },
  { "title": "무법변호사", "author": "Hyeon Seok", "genre": "법정/액션" },
  { "title": "고독한 미식가", "author": "쿠스미 마사유키", "genre": "일상/먹방" },
  { "title": "아도니스", "author": "Shoowa/Okadaya", "genre": "로맨스/BL" },
  { "title": "격기3반", "author": "이학", "genre": "스포츠/액션" }
]
